{
  "pro": ["/static/css/fp.min.css?v=2e35f4de1b64e0b5ed2791280a9c9e44", "/static/riot/common+component.min.js?v=3f0667bcedfe62f1050f853d2b815d36"],
  "test": ["./static/css/fp.css", "./static/riot/component.js", "./static/riot/common.js"],
  "dev": ["./static/css/fp.css", "./static/riot/component.js", "./static/riot/common.js"],
  "header-nav": [{
    "name": "首页",
    "url": "/index"
  }, {
    "name": "协议",
    "url": "/agreement"
  }, {
    "name": "设置",
    "url": "/setting",
    "sub": [{
      "name": "日志",
      "url": "/log"
    }, {
      "name": "密码",
      "url": "/password"
    }]
  }, {
    "name": "查询",
    "url": "/search",
    "sub": [{
      "name": "日志",
      "url": "/log"
    }, {
      "name": "密码",
      "url": "/password"
    }]
  }],
  "lang": {
    "cn": {
      "header": {
        "sitename": "浙江大学教育基金会管理后台",
        "userinfo": {
          "account": "帐号信息",
          "logout": "退出"
        }
      },
      "login": {
        "admin": "管理员登录",
        "user": "捐赠人登录",
        "placehoder": {
          "username": "请输入账号",
          "password": "请输入密码"
        },
        "btn": "登 录",
        "findpass": "忘记密码",
        "fail": "登录失败: 账号密码错误",
        "invalid": "请填写帐号密码",
        "btn:loading": "登 录 中",
        "btn:ok": "登录成功",
        "relogin": "访问失败: 需要重新登录"
      },
      "footer": {
        "icp": "浙ICP备1202106号-2",
        "copyright": "2016-2017 usho",
        "address": "联系地址: 浙江省杭州市西湖区浙大科技园C-608",
        "tel": "联系电话: 0571-85121608"
      }
    }
  }
}
